ancpbids/__init__.py
ancpbids/_version.py
ancpbids/model_base.py
ancpbids/model_v1_10_0.py
ancpbids/model_v1_8_0.py
ancpbids/model_v1_9_0.py
ancpbids/plugin.py
ancpbids/pybids_compat.py
ancpbids/query.py
ancpbids/torch.py
ancpbids/utils.py
ancpbids/plugins/__init__.py
ancpbids/plugins/plugin_dsloader.py
ancpbids/plugins/plugin_dssaver.py
ancpbids/plugins/plugin_dsvalidator.py
ancpbids/plugins/plugin_files_handlers.py
ancpbids/plugins/plugin_metadata_inheritance_principle.py
ancpbids/plugins/plugin_schema_patches.py
ancpbids-0.3.1.dist-info/licenses/LICENSE
tests/__init__.py
tests/base_test_case.py
tests/auto/__init__.py
tests/auto/test_basic.py
tests/auto/test_derivative.py
tests/auto/test_fetch_dataset.py
tests/auto/test_ignored_resources.py
tests/auto/test_query.py
tests/auto/test_regressions.py
tests/auto/test_schema.py
tests/auto/test_validation.py
tests/auto/test_writing.py
tests/manual/__init__.py
tests/manual/test_benchmark.py
tests/manual/test_lazy_load.py
tests/manual/test_performance_regressions.py
tests/optional/__init__.py
tests/optional/test_torch.py
ancpbids-0.3.1.dist-info/METADATA
ancpbids-0.3.1.dist-info/WHEEL
ancpbids-0.3.1.dist-info/top_level.txt
ancpbids-0.3.1.dist-info/RECORD
