Metadata-Version: 2.4
Name: ancpbids
Version: 0.3.1
Summary: Read/write/validate/query BIDS datasets
Home-page: https://github.com/ANCPLabOldenburg/ancp-bids
Author: Erdal Karaca
Author-email: erdal.karaca.de@gmail.com
Maintainer: ANCP Lab, University of Oldenburg
Maintainer-email: currentancp@listserv.uni-oldenburg.de
License: MIT
Platform: OS Independent
Classifier: Development Status :: 3 - Alpha
Classifier: Environment :: Console
Classifier: Intended Audience :: Science/Research
Classifier: License :: OSI Approved :: MIT License
Classifier: Operating System :: OS Independent
Classifier: Programming Language :: Python :: 3.8
Classifier: Programming Language :: Python :: 3.9
Classifier: Programming Language :: Python :: 3.10
Classifier: Programming Language :: Python :: 3.11
Classifier: Programming Language :: Python :: 3.12
Classifier: Topic :: Scientific/Engineering
Requires-Python: >=3.6
License-File: LICENSE
Dynamic: license-file
